CHANGES.txt
COPYRIGHT.txt
LICENSE.txt
MANIFEST.in
README.rst
pytest.ini
setup.cfg
setup.py
tox.ini
docs/Makefile
docs/conf.py
docs/deployment.rst
docs/developers.rst
docs/index.rst
docs/intro.rst
docs/pail.rst
docs/sample-paster.ini
pail/__init__.py
pail/helpers.py
pail/wsgi.py
pail.egg-info/PKG-INFO
pail.egg-info/SOURCES.txt
pail.egg-info/dependency_links.txt
pail.egg-info/entry_points.txt
pail.egg-info/not-zip-safe
pail.egg-info/requires.txt
pail.egg-info/top_level.txt
pail/tests/__init__.py
pail/tests/test_helpers.py
pail/tests/test_wsgi.py